graph_data_generator/__init__.py
graph_data_generator/generators/ALL_GENERATORS.py
graph_data_generator/generators/README.md
graph_data_generator/generators/add_floats.py
graph_data_generator/generators/add_ints.py
graph_data_generator/generators/add_strings.py
graph_data_generator/generators/bool.py
graph_data_generator/generators/catch_phrase.py
graph_data_generator/generators/city.py
graph_data_generator/generators/company_name.py
graph_data_generator/generators/country.py
graph_data_generator/generators/credit_card_expire.py
graph_data_generator/generators/credit_card_number.py
graph_data_generator/generators/credit_card_provider.py
graph_data_generator/generators/date.py
graph_data_generator/generators/email.py
graph_data_generator/generators/exhaustive_random.py
graph_data_generator/generators/exhaustive_random_repeating.py
graph_data_generator/generators/first_name.py
graph_data_generator/generators/float.py
graph_data_generator/generators/float_from_list.py
graph_data_generator/generators/float_range.py
graph_data_generator/generators/hierarchical.py
graph_data_generator/generators/int.py
graph_data_generator/generators/int_from_list.py
graph_data_generator/generators/int_range.py
graph_data_generator/generators/isbn_10.py
graph_data_generator/generators/isbn_13.py
graph_data_generator/generators/job.py
graph_data_generator/generators/last_name.py
graph_data_generator/generators/lorem_paragraphs.py
graph_data_generator/generators/loremtext_sentence.py
graph_data_generator/generators/loremtext_words.py
graph_data_generator/generators/md5.py
graph_data_generator/generators/phone_number.py
graph_data_generator/generators/pure_random.py
graph_data_generator/generators/reference.py
graph_data_generator/generators/ssn.py
graph_data_generator/generators/string_from_csv.py
graph_data_generator/generators/string_from_list.py
graph_data_generator/generators/string_literal.py
graph_data_generator/generators/technical_phrase.py
graph_data_generator/generators/uri.py
graph_data_generator-0.4.1.dist-info/LICENSE.txt
graph_data_generator-0.4.1.dist-info/METADATA
graph_data_generator-0.4.1.dist-info/WHEEL
graph_data_generator-0.4.1.dist-info/RECORD
