Metadata-Version: 2.1
Name: graph-data-generator
Version: 0.4.1
Summary: 
Author: Jason Koo
Author-email: jalakoo@gmail.com
Requires-Python: >=3.9,<4.0
Classifier: Programming Language :: Python :: 3
Classifier: Programming Language :: Python :: 3.9
Classifier: Programming Language :: Python :: 3.10
Classifier: Programming Language :: Python :: 3.11
Requires-Dist: faker (>=19.1.0,<20.0.0)
Requires-Dist: lorem-text (>=2.1,<3.0)
